emon/__init__.py
emon/core/cleaner.py
emon/core/saver.py
emon/core/trainer.py
emon/core/visualizer.py
emon/utils/validator.py
emon-0.0.7.dist-info/licenses/LICENSE
emon-0.0.7.dist-info/METADATA
emon-0.0.7.dist-info/WHEEL
emon-0.0.7.dist-info/entry_points.txt
emon-0.0.7.dist-info/top_level.txt
emon-0.0.7.dist-info/RECORD
