Metadata-Version: 2.4
Name: emon
Version: 0.0.7
Summary: Easy AutoML package to clean, train and export models
Home-page: https://github.com/ABS-EMON/emon
Author: ABS EMON
Author-email: iotandrobotics@gmail.com
Classifier: Programming Language :: Python :: 3
Classifier: License :: OSI Approved :: MIT License
Classifier: Operating System :: OS Independent
Requires-Python: >=3.8
License-File: LICENSE
Requires-Dist: numpy
Requires-Dist: pandas>=1.3.0
Requires-Dist: scikit-learn>=1.0.0
Requires-Dist: xgboost>=1.5.0
Requires-Dist: joblib>=1.1.0
Requires-Dist: seaborn>=0.11.0
Requires-Dist: matplotlib>=3.4.0
Requires-Dist: tqdm>=4.62.0
Requires-Dist: tensorflow>=2.6.0
Dynamic: author
Dynamic: author-email
Dynamic: classifier
Dynamic: description
Dynamic: description-content-type
Dynamic: home-page
Dynamic: license-file
Dynamic: requires-dist
Dynamic: requires-python
Dynamic: summary
